beetsplug/__init__.py
beetsplug/stylize/__init__.py
beetsplug/stylize/plugin.py
beetsplug/stylize/py.typed
beets_stylize-1.2.1.dist-info/LICENSE
beets_stylize-1.2.1.dist-info/METADATA
beets_stylize-1.2.1.dist-info/WHEEL
beets_stylize-1.2.1.dist-info/RECORD
