Metadata-Version: 2.1
Name: beets-stylize
Version: 1.2.1
Summary: Stylize Plugin for Beets
Home-page: https://github.com/kergoth/beets-stylize
License: MIT
Author: Christopher Larson
Author-email: kergoth@gmail.com
Requires-Python: >=3.8,<3.13
Classifier: Development Status :: 5 - Production/Stable
Classifier: Environment :: Plugins
Classifier: License :: OSI Approved :: MIT License
Classifier: Programming Language :: Python
Classifier: Programming Language :: Python :: 3
Classifier: Programming Language :: Python :: 3.8
Classifier: Programming Language :: Python :: 3.9
Classifier: Programming Language :: Python :: 3.10
Classifier: Programming Language :: Python :: 3.11
Classifier: Programming Language :: Python :: 3.12
Classifier: Topic :: Multimedia :: Sound/Audio
Requires-Dist: beets (>=2.0.0,<3.0.0)
Requires-Dist: click (>=8.0.1)
Project-URL: Changelog, https://github.com/kergoth/beets-stylize/releases
Project-URL: Documentation, https://beets-stylize.readthedocs.io
Project-URL: Repository, https://github.com/kergoth/beets-stylize
